projplot/__init__.py
projplot/projplot.py
projplot-1.0.dist-info/LICENSE
projplot-1.0.dist-info/METADATA
projplot-1.0.dist-info/WHEEL
projplot-1.0.dist-info/top_level.txt
projplot-1.0.dist-info/RECORD
