Metadata-Version: 2.1
Name: projplot
Version: 1.0
Summary: Projection plots for assessing convergence of optimization routines
Home-page: https://github.com/kanikadchopra/projplot
Author: Kanika Choptra, Martin Lysy
Author-email: mlysy@uwaterloo.ca
Project-URL: Bug Tracker, https://github.com/mlysy/projplot
Classifier: Programming Language :: Python :: 3
Classifier: License :: OSI Approved :: MIT License
Classifier: Operating System :: OS Independent
License-File: LICENSE
Requires-Dist: numpy
Requires-Dist: pandas
Requires-Dist: seaborn
